haproxy/__init__.py
haproxy/cmds.py
haproxy/conn.py
haproxy/const.py
haproxy/tests/__init__.py
haproxy/tests/test_cmds.py
haproxy/tests/test_conn.py
haproxy_cli-0.7.2.data/scripts/haproxy-cli
haproxy_cli-0.7.2.dist-info/licenses/LICENSE
haproxy_cli-0.7.2.dist-info/METADATA
haproxy_cli-0.7.2.dist-info/WHEEL
haproxy_cli-0.7.2.dist-info/top_level.txt
haproxy_cli-0.7.2.dist-info/RECORD
