Metadata-Version: 2.4
Name: haproxy-cli
Version: 0.7.2
Summary: A tool to interact with HAProxy.
Author: markt.de
Author-email: "markt.de" <github-oss-noreply@markt.de>
Project-URL: Documentation, https://github.com/markt-de/haproxy-cli
Project-URL: Homepage, https://github.com/markt-de/haproxy-cli
Project-URL: Issues, https://github.com/markt-de/haproxy-cli/issues
Project-URL: Repository, https://github.com/markt-de/haproxy-cli.git
Keywords: haproxy,cli
Classifier: Development Status :: 4 - Beta
Classifier: Environment :: Console
Classifier: Intended Audience :: System Administrators
Classifier: Operating System :: POSIX
Classifier: Operating System :: Unix
Classifier: Programming Language :: Python :: 3 :: Only
Classifier: Programming Language :: Python :: 3.11
Classifier: Programming Language :: Python :: 3.12
Classifier: Programming Language :: Python :: 3.13
Classifier: Topic :: Internet :: Proxy Servers
Classifier: Topic :: Software Development :: Libraries :: Python Modules
Classifier: Topic :: System :: Systems Administration
Classifier: Topic :: System :: Networking
Requires-Python: >=3.7
License-File: LICENSE
Provides-Extra: test
Requires-Dist: flake8>=5.0.0; extra == "test"
Requires-Dist: pytest>=6.0.0; extra == "test"
Requires-Dist: pytest-cov>=3.0.0; extra == "test"
Requires-Dist: pyfakefs>=5.0.0; extra == "test"
Dynamic: author
Dynamic: license-file
Dynamic: requires-python
